apistar_contrib/__init__.py
apistar_contrib/compat.py
apistar_contrib/timezone.py
apistar_contrib/unix_time.py
apistar_contrib-0.0.6.dist-info/METADATA
apistar_contrib-0.0.6.dist-info/RECORD
apistar_contrib-0.0.6.dist-info/WHEEL
apistar_contrib-0.0.6.dist-info/top_level.txt
