Metadata-Version: 2.1
Name: apistar-contrib
Version: 0.0.6
Summary: Contrib packages to add on to API Star.
Home-page: https://github.com/ryananguiano/apistar-contrib
Author: Ryan Anguiano
Author-email: ryan.anguiano@gmail.com
License: MIT license
Keywords: apistar contrib
Platform: UNKNOWN
Classifier: Development Status :: 2 - Pre-Alpha
Classifier: Intended Audience :: Developers
Classifier: License :: OSI Approved :: MIT License
Classifier: Natural Language :: English
Classifier: Programming Language :: Python :: 3
Classifier: Programming Language :: Python :: 3.5
Classifier: Programming Language :: Python :: 3.6
Requires-Python: >=3.5
Requires-Dist: apistar (>=0.5)
